partsdb_tools/__init__.py
partsdb_tools/app.py
partsdb_tools/common.py
partsdb_tools/files.py
partsdb_tools/format.py
partsdb_tools/picture.py
partsdb_tools/validate.py
partsdb_tools/packaging/Box.py
partsdb_tools/packaging/BoxPackaging.py
partsdb_tools/packaging/PaperTapeBoxPackaging.py
partsdb_tools/packaging/Reel.py
partsdb_tools/packaging/Tape.py
partsdb_tools/packaging/TapeReelPackaging.py
partsdb_tools/packaging/__init__.py
partsdb_tools/validators/__init__.py
partsdb_tools/validators/orderNumberValidator.py
partsdb_tools-0.2.0.dist-info/licenses/LICENSE
partsdb_tools-0.2.0.dist-info/METADATA
partsdb_tools-0.2.0.dist-info/WHEEL
partsdb_tools-0.2.0.dist-info/entry_points.txt
partsdb_tools-0.2.0.dist-info/top_level.txt
partsdb_tools-0.2.0.dist-info/RECORD
