Metadata-Version: 2.4
Name: partsdb-tools
Version: 0.2.0
Summary: Test tools for partmanager partsdb
Home-page: https://github.com/partmanager/partsdb-tools
Author: sakoPO
Project-URL: Bug Tracker, https://github.com/partmanager/partsdb-tools/issues
Project-URL: Changelog, https://github.com/partmanager/partsdb-tools/releases
Project-URL: Source Code, https://github.com/partmanager/partsdb-tools
Project-URL: Documentation, https://partmanager.github.io/partsdb-tools
Classifier: Programming Language :: Python :: 3
Classifier: Intended Audience :: Developers
Classifier: Intended Audience :: Manufacturing
Classifier: License :: OSI Approved :: GNU General Public License v3 (GPLv3)
Classifier: Operating System :: OS Independent
Requires-Python: >=3.9
License-File: LICENSE
Dynamic: license-file
